reaperdaw/__init__.py
reaperdaw/const.py
reaperdaw/exceptions.py
reaperdaw/models.py
reaperdaw/reaper.py
python_reaperdaw-0.0.7.dist-info/LICENSE
python_reaperdaw-0.0.7.dist-info/METADATA
python_reaperdaw-0.0.7.dist-info/WHEEL
python_reaperdaw-0.0.7.dist-info/top_level.txt
python_reaperdaw-0.0.7.dist-info/RECORD
