Metadata-Version: 2.1
Name: python-reaperdaw
Version: 0.0.7
Summary: Python wrapper for REAPER DAW REST API
Home-page: https://github.com/kubawolanin/python-reaperdaw
Author: Kuba Wolanin
Author-email: kuba.wolanin@gmail.com
License: UNKNOWN
Download-URL: https://github.com/kubawolanin/python-reaperdaw
Platform: UNKNOWN
Classifier: Development Status :: 4 - Beta
Classifier: Intended Audience :: Developers
Classifier: Natural Language :: English
Classifier: Programming Language :: Python :: 3
Classifier: Programming Language :: Python :: 3.6
Classifier: Programming Language :: Python :: 3.7
Classifier: Programming Language :: Python :: 3.8
Classifier: Topic :: Home Automation
Requires-Python: >=3.6
License-File: LICENSE
